{
    "pools": [
        {
            "rolls": 1,
            "entries": [
                {
                    "type": "loot_table",
                    "weight": 100,
                    "value": "chunklock:generic/wood/mangrove",
                    "functions": [
                        {
                            "function": "set_count",
                            "count": 1
                        }
                    ]
                },
                {
                    "type": "item",
                    "weight": 10,
                    "name": "minecraft:vine",
                    "functions": [
                        {
                            "function": "set_count",
                            "count": {
                                "min": 1,
                                "max": 2
                            }
                        }
                    ]
                },
                {
                    "type": "loot_table",
                    "weight": 20,
                    "value": "chunklock:generic/block/mud",
                    "functions": [
                        {
                            "function": "set_count",
                            "count": 1
                        }
                    ]
                },
                {
                    "type": "loot_table",
                    "weight": 10,
                    "value": "chunklock:generic/entity/common_overworld_passive",
                    "functions": [
                        {
                            "function": "set_count",
                            "count": 1
                        }
                    ]
                },
                {
                    "type": "item",
                    "weight": 5,
                    "name": "minecraft:lily_pad",
                    "functions": [
                        {
                            "function": "set_count",
                            "count": {
                                "min": 1,
                                "max": 2
                            }
                        }
                    ]
                },
                {
                    "type": "loot_table",
                    "weight": 5,
                    "value": "chunklock:generic/entity/bee",
                    "functions": [
                        {
                            "function": "set_count",
                            "count": 1
                        }
                    ]
                },
                {
                    "type": "loot_table",
                    "weight": 5,
                    "value": "chunklock:generic/dimension/overworld",
                    "functions": [
                        {
                            "function": "set_count",
                            "count": 1
                        }
                    ]
                }
            ]
        }
    ]
}